[
  {
    "name": "Salary",
    "icons": [
      "briefcase_outline"
    ]
  },
  {
    "name": "Gifts & Bonuses",
    "icons": [
      "gift_outline"
    ]
  },
  {
    "name": "Other Income",
    "icons": [
      "cash_multiple"
    ]
  },
  {
    "name": "Housing",
    "icons": [
      "home",
      "key",
      "bank_outline",
      "wrench",
      "shield",
      "sofa"
    ]
  },
  {
    "name": "Food & Drink",
    "icons": [
      "silverware_fork_knife",
      "shopping",
      "food_fork_drink",
      "cookie",
      "truck",
      "beer"
    ]
  },
  {
    "name": "Transportation",
    "icons": [
      "car",
      "gas_station",
      "bus",
      "wrench_outline"
    ]
  },
  {
    "name": "Health & Wellness",
    "icons": [
      "heart",
      "doctor",
      "pill",
      "dumbbell",
      "leaf"
    ]
  },
  {
    "name": "Personal & Shopping",
    "icons": [
      "shopping_outline",
      "tshirt_crew_outline",
      "cellphone",
      "flower"
    ]
  },
  {
    "name": "Entertainment & Leisure",
    "icons": [
      "party_popper",
      "filmstrip",
      "gamepad_variant",
      "airplane",
      "television_classic"
    ]
  },
  {
    "name": "Education",
    "icons": [
      "book_outline",
      "school_outline",
      "book_open_outline",
      "laptop",
      "presentation",
      "robot"
    ]
  },
  {
    "name": "Savings & Investments",
    "icons": [
      "cash",
      "piggy_bank",
      "chart_line",
      "clock_outline"
    ]
  },
  {
    "name": "Other",
    "icons": [
      "dots_horizontal"
    ]
  }
]
